{
  "case_number": "T 2302-24",
  "nickname": "",
  "summary": "Parterna har ingått ett entreprenadavtal avseende uppförande av ett småhus. Enligt avtalet skulle konsumenten betala i förskott enligt en angiven betalningsplan och ställa ut en bankgaranti på den totala kontraktssumman som säkerhet för sin betalning. Konsumenten har erlagt delbetalning enligt betalningsplanen men har inte ställt ut någon bankgaranti. Målet gäller bl.a. om näringsidkaren haft rätt att häva avtalet. (Svea hovrätt mål T 12562-22)",
  "decision_date": "2024-12-02",
  "publication_time": "2025-04-12T11:32:00",
  "case_id": "3ef7bb36-d2a4-4b39-aa12-dd6159a5b83a",
  "type": "PROVNINGSTILLSTAND",
  "is_precedent": false,
  "court": "Högsta domstolen",
  "court_code": "HDO",
  "keywords": [],
  "legal_areas": [],
  "legal_references": [],
  "referenced_publications": [],
  "pdf_documents": [],
  "case_url": "https://rattspraxis.etjanst.domstol.se/sok/publicering/9a85a0c4-9804-4d9b-85c3-09b0c0a9845c",
  "correlation_number": "9a85a0c4-9804-4d9b-85c3-09b0c0a9845c",
  "full_text": "Sök rättspraxis\nTillbaka\nSkriv ut\nOm avgörandet\nDomstol:\nHögsta domstolen\nMålnummer:\nT 2302-24\nPrövningstillstånd\n2024-12-02\nParterna har ingått ett entreprenadavtal avseende uppförande av ett småhus. Enligt avtalet skulle konsumenten betala i förskott enligt en angiven betalningsplan och ställa ut en bankgaranti på den totala kontraktssumman som säkerhet för sin betalning. Konsumenten har erlagt delbetalning enligt betalningsplanen men har inte ställt ut någon bankgaranti. Målet gäller bl.a. om näringsidkaren haft rätt att häva avtalet. (Svea hovrätt mål T 12562-22)\n- Visa mindre innehåll\nKontakt\nFrågor och svar\nTillgänglighet\nPrenumerera på RSS-flöde"
}